waterbridge/1_Identification of water bridges.py
waterbridge/2_Topological classification of water bridges.py
waterbridge/3_Nomenclature of waterbridges.py
waterbridge/__init__.py
waterbridge/waterbridge.py
waterbridge-0.2.1.dist-info/LICENSE
waterbridge-0.2.1.dist-info/METADATA
waterbridge-0.2.1.dist-info/WHEEL
waterbridge-0.2.1.dist-info/entry_points.txt
waterbridge-0.2.1.dist-info/top_level.txt
waterbridge-0.2.1.dist-info/RECORD
