Metadata-Version: 2.1
Name: waterbridge
Version: 0.2.1
Summary: A tool for identifying water bridges and their topology in RNA–protein complexes.
Home-page: https://github.com/RamanCompChem/waterbridges
Author: Raman Jangra
Author-email: raman.compchem@gmail.com
Classifier: Programming Language :: Python :: 3
Classifier: License :: OSI Approved :: MIT License
Classifier: Operating System :: OS Independent
Requires-Python: >=3.6
License-File: LICENSE
